gpt20b_redteam/__init__.py
gpt20b_redteam/cli.py
gpt20b_redteam/config.py
gpt20b_redteam/logger.py
gpt20b_redteam/metrics.py
gpt20b_redteam/model_wrapper.py
gpt20b_redteam/progress_tracker.py
gpt20b_redteam/runner.py
gpt20b_redteam/probes/__init__.py
gpt20b_redteam/probes/base.py
gpt20b_redteam/probes/covert_channel_capacity.py
gpt20b_redteam/probes/cross_probe_compounding.py
gpt20b_redteam/probes/deception_rewardhack.py
gpt20b_redteam/probes/encoding_evasion.py
gpt20b_redteam/probes/eval_awareness.py
gpt20b_redteam/probes/long_horizon_sleeper.py
gpt20b_redteam/probes/prefix_steering.py
gpt20b_redteam/probes/refusal_boundary_cartography.py
gpt20b_redteam/probes/sabotage_code.py
gpt20b_redteam/probes/tokenizer_frequency_sandbagging.py
gpt_oss_20b_redteam-0.1.5.dist-info/METADATA
gpt_oss_20b_redteam-0.1.5.dist-info/WHEEL
gpt_oss_20b_redteam-0.1.5.dist-info/entry_points.txt
gpt_oss_20b_redteam-0.1.5.dist-info/top_level.txt
gpt_oss_20b_redteam-0.1.5.dist-info/RECORD
