Metadata-Version: 2.4
Name: gpt-oss-20b-redteam
Version: 0.1.5
Summary: GPT-OSS-20B Red-Teaming Harness: Masks, Sandbags, and Sabotage
Author-email: Guy Nachshon <guy@baddon.ai>
License: MIT
Project-URL: Homepage, https://github.com/GuyNachshon/gpt-oss-20b-probing
Project-URL: Repository, https://github.com/GuyNachshon/gpt-oss-20b-probing
Project-URL: Documentation, https://github.com/GuyNachshon/gpt-oss-20b-probing#readme
Project-URL: Issues, https://github.com/GuyNachshon/gpt-oss-20b-probing/issues
Keywords: ai,red-teaming,security,gpt,llm,safety,alignment,misalignment
Classifier: Development Status :: 4 - Beta
Classifier: Intended Audience :: Developers
Classifier: Intended Audience :: Science/Research
Classifier: Programming Language :: Python :: 3
Classifier: Programming Language :: Python :: 3.8
Classifier: Programming Language :: Python :: 3.9
Classifier: Programming Language :: Python :: 3.10
Classifier: Programming Language :: Python :: 3.11
Classifier: Topic :: Scientific/Engineering :: Artificial Intelligence
Classifier: Topic :: Security
Classifier: Topic :: Software Development :: Testing
Requires-Python: >=3.8
Requires-Dist: torch>=2.0.0
Requires-Dist: transformers>=4.30.0
Requires-Dist: accelerate>=0.20.0
Requires-Dist: openai>=1.0.0
Requires-Dist: anthropic>=0.7.0
Requires-Dist: rich>=13.0.0
Requires-Dist: numpy>=1.21.0
Requires-Dist: tqdm>=4.64.0
Requires-Dist: jsonlines>=3.0.0
Requires-Dist: scikit-learn>=1.0.0
Requires-Dist: pandas>=1.3.0
Requires-Dist: scipy>=1.10.1
Provides-Extra: dev
Requires-Dist: pytest>=7.0.0; extra == "dev"
Requires-Dist: black>=22.0.0; extra == "dev"
Requires-Dist: flake8>=5.0.0; extra == "dev"
Requires-Dist: mypy>=1.0.0; extra == "dev"
